prgenius/__init__.py
prgenius/git_utils.py
prgenius/gpt3_utils.py
prgenius/pr_creator.py
PRGenius-1.0.1.dist-info/LICENSE.md
PRGenius-1.0.1.dist-info/METADATA
PRGenius-1.0.1.dist-info/WHEEL
PRGenius-1.0.1.dist-info/entry_points.txt
PRGenius-1.0.1.dist-info/top_level.txt
PRGenius-1.0.1.dist-info/RECORD
