Metadata-Version: 2.1
Name: PRGenius
Version: 1.0.1
Summary: Automates PR creation on GitHub using GPT-3 for description generation based on commit messages.
Home-page: https://github.com/yourusername/PRGenius
Author: Hasanul Banna
Author-email: bannawandoor@gmail.com
License: MIT
Keywords: GitHub PR automation GPT-3
Classifier: Development Status :: 3 - Alpha
Classifier: Intended Audience :: Developers
Classifier: License :: OSI Approved :: MIT License
Classifier: Programming Language :: Python :: 3
Classifier: Programming Language :: Python :: 3.7
Classifier: Programming Language :: Python :: 3.8
Classifier: Programming Language :: Python :: 3.9
Classifier: Programming Language :: Python :: 3.10
License-File: LICENSE.md
Requires-Dist: requests
Requires-Dist: openai
Requires-Dist: python-dotenv
